odoo/addons/product_configurator_sale/README.rst
odoo/addons/product_configurator_sale/__init__.py
odoo/addons/product_configurator_sale/__manifest__.py
odoo/addons/product_configurator_sale/data/menu_product.xml
odoo/addons/product_configurator_sale/demo/res_partner_demo.xml
odoo/addons/product_configurator_sale/i18n/product_configurator_sale.pot
odoo/addons/product_configurator_sale/models/__init__.py
odoo/addons/product_configurator_sale/models/sale.py
odoo/addons/product_configurator_sale/readme/DESCRIPTION.rst
odoo/addons/product_configurator_sale/security/ir.model.access.csv
odoo/addons/product_configurator_sale/static/description/icon.png
odoo/addons/product_configurator_sale/static/description/index.html
odoo/addons/product_configurator_sale/tests/__init__.py
odoo/addons/product_configurator_sale/tests/test_sale.py
odoo/addons/product_configurator_sale/views/sale_view.xml
odoo/addons/product_configurator_sale/wizard/__init__.py
odoo/addons/product_configurator_sale/wizard/product_configurator.py
odoo14_addon_product_configurator_sale-14.0.1.2.0.dist-info/METADATA
odoo14_addon_product_configurator_sale-14.0.1.2.0.dist-info/WHEEL
odoo14_addon_product_configurator_sale-14.0.1.2.0.dist-info/top_level.txt
odoo14_addon_product_configurator_sale-14.0.1.2.0.dist-info/RECORD
