Metadata-Version: 2.1
Name: odoo14-addon-product-configurator-sale
Version: 14.0.1.2.0
Summary: Product configuration interface modules for Sale
Home-page: https://github.com/OCA/product-configurator
Author: Pledra, Odoo Community Association (OCA)
Author-email: support@odoo-community.org
License: AGPL-3
Platform: UNKNOWN
Classifier: Programming Language :: Python
Classifier: Framework :: Odoo
Classifier: Framework :: Odoo :: 14.0
Classifier: License :: OSI Approved :: GNU Affero General Public License v3
Classifier: Development Status :: 4 - Beta
Requires-Python: >=3.6
Requires-Dist: odoo14-addon-product-configurator
Requires-Dist: odoo (<14.1dev,>=14.0a)
